<acceptance-test-run title="Podam should handle immutable Pojos with non generic collections" name="podamShouldHandleImmutablePojosWithNonGenericCollections" steps="9" successful="9" failures="0" skipped="0" ignored="0" pending="0" result="SUCCESS" duration="82" timestamp="2015-07-10T00:17:27.736+01:00">
  <user-story id="uk.co.jemos.podam.test.unit.features.collections.CollectionsTest" name="Collections test" path="uk.co.jemos.podam.test.unit.features.collections"/>
  <tags>
    <tag name="Collections" type="epics"/>
    <tag name="Collections test" type="stories"/>
    <tag name="Collections test" type="story"/>
  </tags>
  <test-step result="SUCCESS" duration="63">
    <description>Given a standard Podam Factory</description>
  </test-step>
  <test-step result="SUCCESS" duration="2">
    <description>When I invoke the factory manufacturing for &lt;span class=&apos;step-parameter&apos;&gt;class uk.co.jemos.podam.test.dto.ImmutableWithNonGenericCollectionsPojo</description>
  </test-step>
  <test-step result="SUCCESS" duration="2">
    <description>Then the Object should not be null</description>
  </test-step>
  <test-step result="SUCCESS" duration="2">
    <description>Then the collection should not be null or empty</description>
  </test-step>
  <test-step result="SUCCESS" duration="2">
    <description>Then the collection should have exactly java.lang.Object@c4231e8 elements</description>
  </test-step>
  <test-step result="SUCCESS" duration="2">
    <description>Then the Set&lt;?&gt; &lt;span class=&apos;step-parameter&apos;&gt;[java.lang.Object@30c1a903 should contain at least one non-empty element</description>
  </test-step>
  <test-step result="SUCCESS" duration="2">
    <description>Then the collection should have exactly java.lang.Object@68a08d18 elements</description>
  </test-step>
  <test-step result="SUCCESS" duration="1">
    <description>Then the Map&lt;?, ?&gt; &lt;span class=&apos;step-parameter&apos;&gt;{java.lang.Object@52760b04=java.lang.Object@51044708 should contain at least one non empty element</description>
  </test-step>
  <test-step result="SUCCESS" duration="2">
    <description>Then the map should have exactly java.lang.Object@624cc07=java.lang.Object@50357562 elements</description>
  </test-step>
</acceptance-test-run>