<acceptance-test-run title="Podam should handle immutable Pojos with non generic collections" name="podamShouldHandleImmutablePojosWithNonGenericCollections" steps="9" successful="9" failures="0" skipped="0" ignored="0" pending="0" result="SUCCESS" duration="28" timestamp="2015-06-14T20:05:34.977+01:00">
  <user-story id="uk.co.jemos.podam.test.unit.features.collections.CollectionsTest" name="Collections test" path="uk.co.jemos.podam.test.unit.features.collections"/>
  <tags>
    <tag name="Collections" type="epics"/>
    <tag name="Collections test" type="stories"/>
    <tag name="Collections test" type="story"/>
  </tags>
  <test-step result="SUCCESS" duration="11">
    <description>Given a standard Podam Factory</description>
  </test-step>
  <test-step result="SUCCESS" duration="3">
    <description>When I invoke the factory manufacturing for &lt;span class=&apos;step-parameter&apos;&gt;class uk.co.jemos.podam.test.dto.ImmutableWithNonGenericCollectionsPojo</description>
  </test-step>
  <test-step result="SUCCESS" duration="1">
    <description>Then the Object should not be null</description>
  </test-step>
  <test-step result="SUCCESS" duration="1">
    <description>Then the collection should not be null or empty</description>
  </test-step>
  <test-step result="SUCCESS" duration="1">
    <description>Then the collection should have exactly java.lang.Object@75288f47 elements</description>
  </test-step>
  <test-step result="SUCCESS" duration="2">
    <description>Then the Set&lt;?&gt; &lt;span class=&apos;step-parameter&apos;&gt;[java.lang.Object@29ff01df should contain at least one non-empty element</description>
  </test-step>
  <test-step result="SUCCESS" duration="1">
    <description>Then the collection should have exactly java.lang.Object@6aaaa66b elements</description>
  </test-step>
  <test-step result="SUCCESS" duration="1">
    <description>Then the Map&lt;?, ?&gt; &lt;span class=&apos;step-parameter&apos;&gt;{java.lang.Object@306ea73f=java.lang.Object@732af580 should contain at least one non empty element</description>
  </test-step>
  <test-step result="SUCCESS" duration="1">
    <description>Then the map should have exactly java.lang.Object@1276caf2=java.lang.Object@40bf2ead elements</description>
  </test-step>
</acceptance-test-run>