{"name":"podamShouldCreatePojosInAccordanceWithCustomDataProviderStrategies","testCaseName":"uk.co.jemos.podam.test.unit.features.dataProviderStrategy.RandomDataProviderStrategyImplInitialisationUnitTest","testSteps":[{"number":1,"description":"Given a Custom Random Data Provider Strategy","duration":0,"startTime":1471797900751,"result":"SUCCESS"},{"number":2,"description":"Given a Podam Factory with custom data provider strategy","duration":22,"startTime":1471797900751,"result":"SUCCESS"},{"number":3,"description":"When I invoke the factory manufacturing for class uk.co.jemos.podam.test.dto.PojoWithMapsAndCollections","duration":1,"startTime":1471797900774,"result":"SUCCESS"},{"number":4,"description":"Then the Object should not be null","duration":0,"startTime":1471797900776,"result":"SUCCESS"},{"number":5,"description":"Then the array of the given type should not be null or empty and contain exactly 2 elements","duration":0,"startTime":1471797900776,"result":"SUCCESS"},{"number":6,"description":"Then the collection should not be null or empty","duration":0,"startTime":1471797900777,"result":"SUCCESS"},{"number":7,"description":"Then the collection should have exactly 3 elements","duration":0,"startTime":1471797900777,"result":"SUCCESS"},{"number":8,"description":"Then the map should not be null or empty","duration":0,"startTime":1471797900778,"result":"SUCCESS"},{"number":9,"description":"Then the map should have exactly 4 elements","duration":0,"startTime":1471797900778,"result":"SUCCESS"}],"userStory":{"id":"uk.co.jemos.podam.test.unit.features.dataProviderStrategy.RandomDataProviderStrategyImplInitialisationUnitTest","storyName":"Random data provider strategy impl initialisation unit test","storyClassName":"uk.co.jemos.podam.test.unit.features.dataProviderStrategy.RandomDataProviderStrategyImplInitialisationUnitTest","path":"uk.co.jemos.podam.test.unit.features.dataProviderStrategy","type":"story"},"title":"Podam should create POJOs in accordance with custom data provider strategies","tags":[{"name":"Data provider strategy/Random data provider strategy impl initialisation unit test","type":"stories"},{"name":"Random data provider strategy impl initialisation unit test","type":"story"},{"name":"Data provider strategy","type":"epics"}],"startTime":1471797900751,"duration":27,"manual":false,"result":"SUCCESS"}