<acceptance-test-run title="Podam should create POJOs in accordance with custom data provider strategies" name="podamShouldCreatePojosInAccordanceWithCustomDataProviderStrategies" steps="9" successful="9" failures="0" skipped="0" ignored="0" pending="0" result="SUCCESS" duration="29" timestamp="2015-06-21T21:03:07.107+01:00">
  <user-story id="uk.co.jemos.podam.test.unit.features.dataProviderStrategy.RandomDataProviderStrategyImplInitialisationUnitTest" name="Random data provider strategy impl initialisation unit test" path="uk.co.jemos.podam.test.unit.features.dataProviderStrategy"/>
  <tags>
    <tag name="Data provider strategy" type="epics"/>
    <tag name="Random data provider strategy impl initialisation unit test" type="stories"/>
    <tag name="Random data provider strategy impl initialisation unit test" type="story"/>
  </tags>
  <test-step result="SUCCESS" duration="1">
    <description>Given a Custom Random Data Provider Strategy</description>
  </test-step>
  <test-step result="SUCCESS" duration="9">
    <description>Given a Podam Factory with custom data provider strategy</description>
  </test-step>
  <test-step result="SUCCESS" duration="2">
    <description>When I invoke the factory manufacturing for &lt;span class=&apos;step-parameter&apos;&gt;class uk.co.jemos.podam.test.dto.PojoWithMapsAndCollections</description>
  </test-step>
  <test-step result="SUCCESS" duration="2">
    <description>Then the Object should not be null</description>
  </test-step>
  <test-step result="SUCCESS" duration="2">
    <description>Then the array of the given type should not be null or empty and contain exactly gRz2wyN5Xc} elements</description>
  </test-step>
  <test-step result="SUCCESS" duration="2">
    <description>Then the collection should not be null or empty</description>
  </test-step>
  <test-step result="SUCCESS" duration="2">
    <description>Then the collection should have exactly true elements</description>
  </test-step>
  <test-step result="SUCCESS" duration="2">
    <description>Then the map should not be null or empty</description>
  </test-step>
  <test-step result="SUCCESS" duration="2">
    <description>Then the map should have exactly 1757671380=333522652976471 elements</description>
  </test-step>
</acceptance-test-run>