<acceptance-test-run title="Invoking Podam on a POJO with a circular constructor (e.g. java.net.URL) leads to a null POJO" name="podamCannotHandleCircularConstructors" steps="3" successful="3" failures="0" skipped="0" ignored="0" pending="0" result="SUCCESS" duration="78" timestamp="2016-10-09T18:32:53.590+03:00">
  <user-story id="uk.co.jemos.podam.test.unit.features.edgeCases.AbnormalPojosTest" name="Abnormal pojos test" path="uk.co.jemos.podam.test.unit.features.edgeCases"/>
  <tags>
    <tag name="Edge cases" type="epics"/>
    <tag name="Edge cases/Abnormal pojos test" type="stories"/>
    <tag name="Abnormal pojos test" type="story"/>
  </tags>
  <test-step result="SUCCESS" duration="1">
    <description>Given a standard Podam Factory</description>
  </test-step>
  <test-step result="SUCCESS" duration="74">
    <description>When I invoke the factory manufacturing for class java.net.URL</description>
  </test-step>
  <test-step result="SUCCESS" duration="1">
    <description>Then the Pojo should be null</description>
  </test-step>
</acceptance-test-run>