{"name":"podamCannotFillInterfaceAttributesIfTheExternalFactoryDoesNotManufactureTheRightType","testCaseName":"uk.co.jemos.podam.test.unit.features.externalFactory.ExternalFactoryUnitTest","testSteps":[{"number":1,"description":"Given an external factory","duration":0,"startTime":1476027175271,"result":"SUCCESS"},{"number":2,"description":"Given a Podam Factory with external factory","duration":1,"startTime":1476027175271,"result":"SUCCESS"},{"number":3,"description":"When I invoke the factory manufacturing for class uk.co.jemos.podam.test.dto.PojoWithInterfaces","duration":6,"startTime":1476027175275,"result":"SUCCESS"},{"number":4,"description":"Then the Object should not be null","duration":1,"startTime":1476027175281,"result":"SUCCESS"},{"number":5,"description":"Then the two objects interface uk.co.jemos.podam.test.dto.ObjectExt and interface uk.co.jemos.podam.test.dto.ObjectExt should be equal","duration":0,"startTime":1476027175282,"result":"SUCCESS"},{"number":6,"description":"Then the two objects interface uk.co.jemos.podam.test.dto.InterfacePojo and interface uk.co.jemos.podam.test.dto.InterfacePojo should be equal","duration":5,"startTime":1476027175283,"result":"SUCCESS"},{"number":7,"description":"Then the two objects 0 and 0 should be equal","duration":0,"startTime":1476027175289,"result":"SUCCESS"}],"userStory":{"id":"uk.co.jemos.podam.test.unit.features.externalFactory.ExternalFactoryUnitTest","storyName":"External factory unit test","storyClassName":"uk.co.jemos.podam.test.unit.features.externalFactory.ExternalFactoryUnitTest","path":"uk.co.jemos.podam.test.unit.features.externalFactory","type":"story"},"title":"Podam cannot fill interface attributes if the external factory does not manufacture the right type","tags":[{"name":"External factory unit test","type":"story"},{"name":"External factory","type":"epics"},{"name":"External factory/External factory unit test","type":"stories"}],"startTime":1476027175270,"duration":20,"manual":false,"result":"SUCCESS"}