{"name":"Running one factory should return a basic POJO filled with basic types","testSteps":[{"number":1,"description":"Given I have a Podam Factory for simple types","duration":283,"startTime":1432504923200,"result":"SUCCESS","children":[{"number":2,"description":"Provide podam factory","duration":28,"startTime":1432504923451,"result":"SUCCESS"}]},{"number":3,"description":"When I invoke Podam on a POJO with only basic types","duration":33,"startTime":1432504923484,"result":"SUCCESS","children":[{"number":4,"description":"Invoke podam on pojo with only basic types","duration":27,"startTime":1432504923488,"result":"SUCCESS"}]},{"number":5,"description":"Then The returned simple POJO should not be null","duration":11,"startTime":1432504923517,"result":"SUCCESS","children":[{"number":6,"description":"Validate returned pojo is not null","duration":5,"startTime":1432504923520,"result":"SUCCESS"}]},{"number":7,"description":"And The returned simple POJO should have its basic types filled with data","duration":7,"startTime":1432504923529,"result":"SUCCESS","children":[{"number":8,"description":"Then the returned pojo should have its basic fields validated with data","duration":3,"startTime":1432504923531,"result":"SUCCESS"}]}],"userStory":{"id":"basic-types","storyName":"Basic-types","path":"stories/jvmTypes/basicTypes/basic-types.story","type":"story"},"title":"Running one factory should return a basic POJO filled with basic types","tags":[{"name":"Basic-types","type":"story"},{"name":"Jvm types/Basic types","type":"feature"},{"name":"Podam should fill in types contained in the JVM\nAs a user\nI want Podam Factory to fill in object graphs for all native types\nSo that I can count on the framework to fill in basic POJOs","type":"JVMTypes\n\nStory"},{"name":"Basic types/Basic-types","type":"story"},{"name":"Jvm types","type":"capability"},{"name":"Basic types/Basic types","type":"story"}],"startTime":1432504923112,"duration":435,"manual":false,"result":"SUCCESS"}